[
    {
        "날짜": 201001,
        "국가명": "한국",
        "관광객수": 1118261,
        "출입국": "국민해외관광객"
    },
    {
        "날짜": 201002,
        "국가명": "한국",
        "관광객수": 908103,
        "출입국": "국민해외관광객"
    },
    {
        "날짜": 201003,
        "국가명": "한국",
        "관광객수": 950185,
        "출입국": "국민해외관광객"
    },
    {
        "날짜": 201004,
        "국가명": "한국",
        "관광객수": 935904,
        "출입국": "국민해외관광객"
    },
    {
        "날짜": 201005,
        "국가명": "한국",
        "관광객수": 1023815,
        "출입국": "국민해외관광객"
    },
    {
        "날짜": 201006,
        "국가명": "한국",
        "관광객수": 997597,
        "출입국": "국민해외관광객"
    },
    {
        "날짜": 201007,
        "국가명": "한국",
        "관광객수": 1223723,
        "출입국": "국민해외관광객"
    },
    {
        "날짜": 201008,
        "국가명": "한국",
        "관광객수": 1235742,
        "출입국": "국민해외관광객"
    },
    {
        "날짜": 201009,
        "국가명": "한국",
        "관광객수": 1013123,
        "출입국": "국민해외관광객"
    },
    {
        "날짜": 201010,
        "국가명": "한국",
        "관광객수": 1055581,
        "출입국": "국민해외관광객"
    },
    {
        "날짜": 201011,
        "국가명": "한국",
        "관광객수": 1004902,
        "출입국": "국민해외관광객"
    },
    {
        "날짜": 201012,
        "국가명": "한국",
        "관광객수": 1021428,
        "출입국": "국민해외관광객"
    },
    {
        "날짜": 201101,
        "국가명": "한국",
        "관광객수": 1268007,
        "출입국": "국민해외관광객"
    },
    {
        "날짜": 201102,
        "국가명": "한국",
        "관광객수": 1091628,
        "출입국": "국민해외관광객"
    },
    {
        "날짜": 201103,
        "국가명": "한국",
        "관광객수": 868694,
        "출입국": "국민해외관광객"
    },
    {
        "날짜": 201104,
        "국가명": "한국",
        "관광객수": 867487,
        "출입국": "국민해외관광객"
    },
    {
        "날짜": 201105,
        "국가명": "한국",
        "관광객수": 1014409,
        "출입국": "국민해외관광객"
    },
    {
        "날짜": 201106,
        "국가명": "한국",
        "관광객수": 1053658,
        "출입국": "국민해외관광객"
    },
    {
        "날짜": 201107,
        "국가명": "한국",
        "관광객수": 1241629,
        "출입국": "국민해외관광객"
    },
    {
        "날짜": 201108,
        "국가명": "한국",
        "관광객수": 1247222,
        "출입국": "국민해외관광객"
    },
    {
        "날짜": 201109,
        "국가명": "한국",
        "관광객수": 1013507,
        "출입국": "국민해외관광객"
    },
    {
        "날짜": 201110,
        "국가명": "한국",
        "관광객수": 1032589,
        "출입국": "국민해외관광객"
    },
    {
        "날짜": 201111,
        "국가명": "한국",
        "관광객수": 974255,
        "출입국": "국민해외관광객"
    },
    {
        "날짜": 201112,
        "국가명": "한국",
        "관광객수": 1020648,
        "출입국": "국민해외관광객"
    },
    {
        "날짜": 201201,
        "국가명": "한국",
        "관광객수": 1200782,
        "출입국": "국민해외관광객"
    },
    {
        "날짜": 201202,
        "국가명": "한국",
        "관광객수": 1150334,
        "출입국": "국민해외관광객"
    },
    {
        "날짜": 201203,
        "국가명": "한국",
        "관광객수": 1018952,
        "출입국": "국민해외관광객"
    },
    {
        "날짜": 201204,
        "국가명": "한국",
        "관광객수": 1018645,
        "출입국": "국민해외관광객"
    },
    {
        "날짜": 201205,
        "국가명": "한국",
        "관광객수": 1096950,
        "출입국": "국민해외관광객"
    },
    {
        "날짜": 201206,
        "국가명": "한국",
        "관광객수": 1109273,
        "출입국": "국민해외관광객"
    },
    {
        "날짜": 201207,
        "국가명": "한국",
        "관광객수": 1305418,
        "출입국": "국민해외관광객"
    },
    {
        "날짜": 201208,
        "국가명": "한국",
        "관광객수": 1334651,
        "출입국": "국민해외관광객"
    },
    {
        "날짜": 201209,
        "국가명": "한국",
        "관광객수": 1059709,
        "출입국": "국민해외관광객"
    },
    {
        "날짜": 201210,
        "국가명": "한국",
        "관광객수": 1154742,
        "출입국": "국민해외관광객"
    },
    {
        "날짜": 201211,
        "국가명": "한국",
        "관광객수": 1117550,
        "출입국": "국민해외관광객"
    },
    {
        "날짜": 201212,
        "국가명": "한국",
        "관광객수": 1169970,
        "출입국": "국민해외관광객"
    },
    {
        "날짜": 201301,
        "국가명": "한국",
        "관광객수": 1425900,
        "출입국": "국민해외관광객"
    },
    {
        "날짜": 201302,
        "국가명": "한국",
        "관광객수": 1184807,
        "출입국": "국민해외관광객"
    },
    {
        "날짜": 201303,
        "국가명": "한국",
        "관광객수": 1113946,
        "출입국": "국민해외관광객"
    },
    {
        "날짜": 201304,
        "국가명": "한국",
        "관광객수": 1097420,
        "출입국": "국민해외관광객"
    },
    {
        "날짜": 201305,
        "국가명": "한국",
        "관광객수": 1185405,
        "출입국": "국민해외관광객"
    },
    {
        "날짜": 201306,
        "국가명": "한국",
        "관광객수": 1221491,
        "출입국": "국민해외관광객"
    },
    {
        "날짜": 201307,
        "국가명": "한국",
        "관광객수": 1417422,
        "출입국": "국민해외관광객"
    },
    {
        "날짜": 201308,
        "국가명": "한국",
        "관광객수": 1407186,
        "출입국": "국민해외관광객"
    },
    {
        "날짜": 201309,
        "국가명": "한국",
        "관광객수": 1195238,
        "출입국": "국민해외관광객"
    },
    {
        "날짜": 201310,
        "국가명": "한국",
        "관광객수": 1239143,
        "출입국": "국민해외관광객"
    },
    {
        "날짜": 201311,
        "국가명": "한국",
        "관광객수": 1154064,
        "출입국": "국민해외관광객"
    },
    {
        "날짜": 201312,
        "국가명": "한국",
        "관광객수": 1204463,
        "출입국": "국민해외관광객"
    },
    {
        "날짜": 201401,
        "국가명": "한국",
        "관광객수": 1468903,
        "출입국": "국민해외관광객"
    },
    {
        "날짜": 201402,
        "국가명": "한국",
        "관광객수": 1312683,
        "출입국": "국민해외관광객"
    },
    {
        "날짜": 201403,
        "국가명": "한국",
        "관광객수": 1150959,
        "출입국": "국민해외관광객"
    },
    {
        "날짜": 201404,
        "국가명": "한국",
        "관광객수": 1179885,
        "출입국": "국민해외관광객"
    },
    {
        "날짜": 201405,
        "국가명": "한국",
        "관광객수": 1223003,
        "출입국": "국민해외관광객"
    },
    {
        "날짜": 201406,
        "국가명": "한국",
        "관광객수": 1270439,
        "출입국": "국민해외관광객"
    },
    {
        "날짜": 201407,
        "국가명": "한국",
        "관광객수": 1454795,
        "출입국": "국민해외관광객"
    },
    {
        "날짜": 201408,
        "국가명": "한국",
        "관광객수": 1547193,
        "출입국": "국민해외관광객"
    },
    {
        "날짜": 201409,
        "국가명": "한국",
        "관광객수": 1321293,
        "출입국": "국민해외관광객"
    },
    {
        "날짜": 201410,
        "국가명": "한국",
        "관광객수": 1432100,
        "출입국": "국민해외관광객"
    },
    {
        "날짜": 201411,
        "국가명": "한국",
        "관광객수": 1288754,
        "출입국": "국민해외관광객"
    },
    {
        "날짜": 201412,
        "국가명": "한국",
        "관광객수": 1430677,
        "출입국": "국민해외관광객"
    },
    {
        "날짜": 201501,
        "국가명": "한국",
        "관광객수": 1834538,
        "출입국": "국민해외관광객"
    },
    {
        "날짜": 201502,
        "국가명": "한국",
        "관광객수": 1445609,
        "출입국": "국민해외관광객"
    },
    {
        "날짜": 201503,
        "국가명": "한국",
        "관광객수": 1416683,
        "출입국": "국민해외관광객"
    },
    {
        "날짜": 201504,
        "국가명": "한국",
        "관광객수": 1495460,
        "출입국": "국민해외관광객"
    },
    {
        "날짜": 201505,
        "국가명": "한국",
        "관광객수": 1579265,
        "출입국": "국민해외관광객"
    },
    {
        "날짜": 201506,
        "국가명": "한국",
        "관광객수": 1373551,
        "출입국": "국민해외관광객"
    },
    {
        "날짜": 201507,
        "국가명": "한국",
        "관광객수": 1675332,
        "출입국": "국민해외관광객"
    },
    {
        "날짜": 201508,
        "국가명": "한국",
        "관광객수": 1835249,
        "출입국": "국민해외관광객"
    },
    {
        "날짜": 201509,
        "국가명": "한국",
        "관광객수": 1511657,
        "출입국": "국민해외관광객"
    },
    {
        "날짜": 201510,
        "국가명": "한국",
        "관광객수": 1735308,
        "출입국": "국민해외관광객"
    },
    {
        "날짜": 201511,
        "국가명": "한국",
        "관광객수": 1626063,
        "출입국": "국민해외관광객"
    },
    {
        "날짜": 201512,
        "국가명": "한국",
        "관광객수": 1781715,
        "출입국": "국민해외관광객"
    },
    {
        "날짜": 201601,
        "국가명": "한국",
        "관광객수": 2112337,
        "출입국": "국민해외관광객"
    },
    {
        "날짜": 201602,
        "국가명": "한국",
        "관광객수": 1876928,
        "출입국": "국민해외관광객"
    },
    {
        "날짜": 201603,
        "국가명": "한국",
        "관광객수": 1569162,
        "출입국": "국민해외관광객"
    },
    {
        "날짜": 201604,
        "국가명": "한국",
        "관광객수": 1636597,
        "출입국": "국민해외관광객"
    },
    {
        "날짜": 201605,
        "국가명": "한국",
        "관광객수": 1656728,
        "출입국": "국민해외관광객"
    },
    {
        "날짜": 201606,
        "국가명": "한국",
        "관광객수": 1778317,
        "출입국": "국민해외관광객"
    },
    {
        "날짜": 201607,
        "국가명": "한국",
        "관광객수": 2086068,
        "출입국": "국민해외관광객"
    },
    {
        "날짜": 201608,
        "국가명": "한국",
        "관광객수": 2064241,
        "출입국": "국민해외관광객"
    },
    {
        "날짜": 201609,
        "국가명": "한국",
        "관광객수": 1904524,
        "출입국": "국민해외관광객"
    },
    {
        "날짜": 201610,
        "국가명": "한국",
        "관광객수": 1865552,
        "출입국": "국민해외관광객"
    },
    {
        "날짜": 201611,
        "국가명": "한국",
        "관광객수": 1825701,
        "출입국": "국민해외관광객"
    },
    {
        "날짜": 201612,
        "국가명": "한국",
        "관광객수": 2007035,
        "출입국": "국민해외관광객"
    },
    {
        "날짜": 201701,
        "국가명": "한국",
        "관광객수": 2343048,
        "출입국": "국민해외관광객"
    },
    {
        "날짜": 201702,
        "국가명": "한국",
        "관광객수": 2231269,
        "출입국": "국민해외관광객"
    },
    {
        "날짜": 201703,
        "국가명": "한국",
        "관광객수": 1940542,
        "출입국": "국민해외관광객"
    },
    {
        "날짜": 201704,
        "국가명": "한국",
        "관광객수": 2003943,
        "출입국": "국민해외관광객"
    },
    {
        "날짜": 201705,
        "국가명": "한국",
        "관광객수": 2003834,
        "출입국": "국민해외관광객"
    },
    {
        "날짜": 201706,
        "국가명": "한국",
        "관광객수": 2098126,
        "출입국": "국민해외관광객"
    },
    {
        "날짜": 201707,
        "국가명": "한국",
        "관광객수": 2389447,
        "출입국": "국민해외관광객"
    },
    {
        "날짜": 201708,
        "국가명": "한국",
        "관광객수": 2385301,
        "출입국": "국민해외관광객"
    },
    {
        "날짜": 201709,
        "국가명": "한국",
        "관광객수": 2236500,
        "출입국": "국민해외관광객"
    },
    {
        "날짜": 201710,
        "국가명": "한국",
        "관광객수": 2231748,
        "출입국": "국민해외관광객"
    },
    {
        "날짜": 201711,
        "국가명": "한국",
        "관광객수": 2227747,
        "출입국": "국민해외관광객"
    },
    {
        "날짜": 201712,
        "국가명": "한국",
        "관광객수": 2404942,
        "출입국": "국민해외관광객"
    },
    {
        "날짜": 201801,
        "국가명": "한국",
        "관광객수": 2866780,
        "출입국": "국민해외관광객"
    },
    {
        "날짜": 201802,
        "국가명": "한국",
        "관광객수": 2311009,
        "출입국": "국민해외관광객"
    },
    {
        "날짜": 201803,
        "국가명": "한국",
        "관광객수": 2252565,
        "출입국": "국민해외관광객"
    },
    {
        "날짜": 201804,
        "국가명": "한국",
        "관광객수": 2230200,
        "출입국": "국민해외관광객"
    },
    {
        "날짜": 201805,
        "국가명": "한국",
        "관광객수": 2331565,
        "출입국": "국민해외관광객"
    },
    {
        "날짜": 201806,
        "국가명": "한국",
        "관광객수": 2323986,
        "출입국": "국민해외관광객"
    },
    {
        "날짜": 201807,
        "국가명": "한국",
        "관광객수": 2495297,
        "출입국": "국민해외관광객"
    },
    {
        "날짜": 201808,
        "국가명": "한국",
        "관광객수": 2519860,
        "출입국": "국민해외관광객"
    },
    {
        "날짜": 201809,
        "국가명": "한국",
        "관광객수": 2225756,
        "출입국": "국민해외관광객"
    },
    {
        "날짜": 201810,
        "국가명": "한국",
        "관광객수": 2347876,
        "출입국": "국민해외관광객"
    },
    {
        "날짜": 201811,
        "국가명": "한국",
        "관광객수": 2295810,
        "출입국": "국민해외관광객"
    },
    {
        "날짜": 201812,
        "국가명": "한국",
        "관광객수": 2495279,
        "출입국": "국민해외관광객"
    },
    {
        "날짜": 201901,
        "국가명": "한국",
        "관광객수": 2912331,
        "출입국": "국민해외관광객"
    },
    {
        "날짜": 201902,
        "국가명": "한국",
        "관광객수": 2617946,
        "출입국": "국민해외관광객"
    },
    {
        "날짜": 201903,
        "국가명": "한국",
        "관광객수": 2334153,
        "출입국": "국민해외관광객"
    },
    {
        "날짜": 201904,
        "국가명": "한국",
        "관광객수": 2246417,
        "출입국": "국민해외관광객"
    },
    {
        "날짜": 201905,
        "국가명": "한국",
        "관광객수": 2401204,
        "출입국": "국민해외관광객"
    },
    {
        "날짜": 201906,
        "국가명": "한국",
        "관광객수": 2495798,
        "출입국": "국민해외관광객"
    },
    {
        "날짜": 201907,
        "국가명": "한국",
        "관광객수": 2642585,
        "출입국": "국민해외관광객"
    },
    {
        "날짜": 201908,
        "국가명": "한국",
        "관광객수": 2427634,
        "출입국": "국민해외관광객"
    },
    {
        "날짜": 201909,
        "국가명": "한국",
        "관광객수": 2049830,
        "출입국": "국민해외관광객"
    },
    {
        "날짜": 201910,
        "국가명": "한국",
        "관광객수": 2153847,
        "출입국": "국민해외관광객"
    },
    {
        "날짜": 201911,
        "국가명": "한국",
        "관광객수": 2090192,
        "출입국": "국민해외관광객"
    },
    {
        "날짜": 201912,
        "국가명": "한국",
        "관광객수": 2342310,
        "출입국": "국민해외관광객"
    },
    {
        "날짜": 202001,
        "국가명": "한국",
        "관광객수": 2513030,
        "출입국": "국민해외관광객"
    },
    {
        "날짜": 202002,
        "국가명": "한국",
        "관광객수": 1046779,
        "출입국": "국민해외관광객"
    },
    {
        "날짜": 202003,
        "국가명": "한국",
        "관광객수": 143366,
        "출입국": "국민해외관광객"
    },
    {
        "날짜": 202004,
        "국가명": "한국",
        "관광객수": 31425,
        "출입국": "국민해외관광객"
    },
    {
        "날짜": 202005,
        "국가명": "한국",
        "관광객수": 37802,
        "출입국": "국민해외관광객"
    },
    {
        "날짜": 202006,
        "국가명": "한국",
        "관광객수": 48353,
        "출입국": "국민해외관광객"
    },
    {
        "날짜": 202007,
        "국가명": "한국",
        "관광객수": 65936,
        "출입국": "국민해외관광객"
    },
    {
        "날짜": 202008,
        "국가명": "한국",
        "관광객수": 88888,
        "출입국": "국민해외관광객"
    },
    {
        "날짜": 202009,
        "국가명": "한국",
        "관광객수": 76798,
        "출입국": "국민해외관광객"
    },
    {
        "날짜": 202010,
        "국가명": "한국",
        "관광객수": 71970,
        "출입국": "국민해외관광객"
    },
    {
        "날짜": 202011,
        "국가명": "한국",
        "관광객수": 70686,
        "출입국": "국민해외관광객"
    },
    {
        "날짜": 202012,
        "국가명": "한국",
        "관광객수": 80973,
        "출입국": "국민해외관광객"
    }
]